BeautifulRequests/__init__.py
BeautifulRequests/beautiful.py
BeautifulRequests-0.1.dist-info/DESCRIPTION.rst
BeautifulRequests-0.1.dist-info/METADATA
BeautifulRequests-0.1.dist-info/RECORD
BeautifulRequests-0.1.dist-info/WHEEL
BeautifulRequests-0.1.dist-info/metadata.json
BeautifulRequests-0.1.dist-info/top_level.txt
